remarx/__init__.py
remarx/utils.py
remarx/app/__init__.py
remarx/app/corpus_builder.py
remarx/app/log_viewer.py
remarx/app/quote_finder.py
remarx/app/utils.py
remarx/quotation/__init__.py
remarx/quotation/consolidate.py
remarx/quotation/embeddings.py
remarx/quotation/find_quotes.py
remarx/quotation/pairs.py
remarx/sentence/__init__.py
remarx/sentence/segment.py
remarx/sentence/corpus/__init__.py
remarx/sentence/corpus/alto_input.py
remarx/sentence/corpus/base_input.py
remarx/sentence/corpus/create.py
remarx/sentence/corpus/tei_input.py
remarx/sentence/corpus/text_input.py
remarx-1.0.1.dist-info/METADATA
remarx-1.0.1.dist-info/WHEEL
remarx-1.0.1.dist-info/entry_points.txt
remarx-1.0.1.dist-info/licenses/LICENSE
remarx-1.0.1.dist-info/RECORD
