Metadata-Version: 2.4
Name: remarx
Version: 1.0.1
Summary: Code for identifying Marx quotes associated with the CDH project Citing Marx
Author-email: Center for Digital Humanities at Princeton <cdh@princeton.edu>
License: Apache-2.0
License-File: LICENSE
Classifier: Development Status :: 3 - Alpha
Classifier: Intended Audience :: Science/Research
Classifier: Operating System :: OS Independent
Classifier: Programming Language :: Python :: 3
Classifier: Programming Language :: Python :: 3.12
Classifier: Topic :: Scientific/Engineering :: Information Analysis
Classifier: Topic :: Text Processing
Requires-Python: >=3.12
Requires-Dist: fastapi
Requires-Dist: ipython
Requires-Dist: marimo>=0.13.11
Requires-Dist: natsort>=8.4.0
Requires-Dist: neuxml>=1
Requires-Dist: numpy
Requires-Dist: pip
Requires-Dist: polars>=0.20.4
Requires-Dist: ruff
Requires-Dist: sentence-transformers
Requires-Dist: spacy
Requires-Dist: transformers[torch]
Requires-Dist: uvicorn
Requires-Dist: voyager>=2.1.0
Provides-Extra: dev
Requires-Dist: bs4; extra == 'dev'
Requires-Dist: coverage[toml]; extra == 'dev'
Requires-Dist: marimo[lsp]; extra == 'dev'
Requires-Dist: mkdocs; extra == 'dev'
Requires-Dist: mkdocs-material; extra == 'dev'
Requires-Dist: mkdocstrings[python]; extra == 'dev'
Requires-Dist: pre-commit; extra == 'dev'
Requires-Dist: pytest; extra == 'dev'
Requires-Dist: pytest-asyncio; extra == 'dev'
Requires-Dist: pytest-cov; extra == 'dev'
Requires-Dist: ruff; extra == 'dev'
Provides-Extra: docs
Requires-Dist: mkdocs; extra == 'docs'
Requires-Dist: mkdocs-material; extra == 'docs'
Requires-Dist: mkdocstrings[python]; extra == 'docs'
Provides-Extra: html
Requires-Dist: bs4; extra == 'html'
Provides-Extra: test
Requires-Dist: coverage[toml]; extra == 'test'
Requires-Dist: pytest; extra == 'test'
Requires-Dist: pytest-asyncio; extra == 'test'
Requires-Dist: pytest-cov; extra == 'test'
